MANIFEST.in
README.md
requirements.txt
setup.py
aker/__init__.py
aker/aker.ini
aker/aker.py
aker/commands.py
aker/config.py
aker/hosts.py
aker/idp_factory.py
aker/popup.py
aker/session.py
aker/snoop.py
aker/ssh_client.py
aker/tui.py
aker/user.py
aker.egg-info/PKG-INFO
aker.egg-info/SOURCES.txt
aker.egg-info/dependency_links.txt
aker.egg-info/entry_points.txt
aker.egg-info/requires.txt
aker.egg-info/top_level.txt
aker/cli/__init__.py
aker/cli/aker.py
aker/cli/akerctl.py
aker/idp/__init__.py
aker/idp/ipa.py
aker/idp/json.py