Metadata-Version: 1.1
Name: aker
Version: 0.5.0
Summary: Aker SSH gateway
Home-page: https://github.com/aker-gateway/Aker
Author: Ahmed Nazmy
Author-email: ahmed@nazmy.io
License: UNKNOWN
Platform: UNKNOWN
Classifier: Programming Language :: Python :: 2
Classifier: Operating System :: OS Independent
